websauna.blog-1.0a2-py3.5-nspkg.pth
websauna/blog/__init__.py
websauna/blog/admins.py
websauna/blog/adminviews.py
websauna/blog/demo.py
websauna/blog/models.py
websauna/blog/rss.py
websauna/blog/templatevars.py
websauna/blog/views.py
websauna/blog/conf/development-secrets.ini
websauna/blog/conf/development.ini
websauna/blog/conf/test.ini
websauna/blog/demotemplates/site/meta.html
websauna/blog/demotemplates/site/nav.html
websauna/blog/static/logo.png
websauna/blog/static/theme.css
websauna/blog/templates/admin/post_show.html
websauna/blog/templates/blog/admin_panel.html
websauna/blog/templates/blog/base.html
websauna/blog/templates/blog/blog_roll.html
websauna/blog/templates/blog/blog_roll_content.html
websauna/blog/templates/blog/byline.html
websauna/blog/templates/blog/commenting.html
websauna/blog/templates/blog/post.html
websauna/blog/templates/blog/rss_head.html
websauna/blog/templates/blog/social_head.html
websauna/blog/templates/blog/tag_roll.html
websauna/blog/templates/blog/tags_line.html
websauna/blog/templates/blog/title.html
websauna/blog/tests/__init__.py
websauna/blog/tests/functional/conftest.py
websauna/blog/tests/functional/test_blog_roll.py
websauna/blog/tests/functional/test_post.py
websauna/blog/tests/functional/test_rss.py
websauna/blog/tests/functional/test_tag.py
websauna/blog/tests/model/conftest.py
websauna/blog/tests/model/test_permission.py
websauna/blog/tests/model/test_slug.py
websauna.blog-1.0a2.dist-info/DESCRIPTION.rst
websauna.blog-1.0a2.dist-info/METADATA
websauna.blog-1.0a2.dist-info/RECORD
websauna.blog-1.0a2.dist-info/WHEEL
websauna.blog-1.0a2.dist-info/entry_points.txt
websauna.blog-1.0a2.dist-info/metadata.json
websauna.blog-1.0a2.dist-info/namespace_packages.txt
websauna.blog-1.0a2.dist-info/top_level.txt
