Metadata-Version: 2.0
Name: websauna.blog
Version: 1.0a2
Summary: Blog add on for Websauna
Home-page: https://websauna.org
Author: Mikko Ohtamaa
Author-email: mikko@opensourcehacker.com
License: MIT
Keywords: web websauna pyramid
Platform: UNKNOWN
Classifier: Development Status :: 3 - Alpha
Classifier: Framework :: Pyramid
Classifier: Intended Audience :: Developers
Classifier: License :: OSI Approved :: MIT License
Classifier: Programming Language :: Python :: 3
Classifier: Programming Language :: Python :: 3.5
Classifier: Programming Language :: Python :: 3.6
Classifier: Programming Language :: Python :: Implementation :: CPython
Classifier: Topic :: Internet :: WWW/HTTP
Classifier: Topic :: Internet :: WWW/HTTP :: Dynamic Content
Classifier: Topic :: Internet :: WWW/HTTP :: WSGI :: Application
Classifier: Topic :: Internet :: WWW/HTTP :: WSGI
Requires-Dist: websauna
Requires-Dist: Markdown
Requires-Dist: rfeed
Provides-Extra: dev
Requires-Dist: pyroma (==2.2); extra == 'dev'
Requires-Dist: sphinx (>=1.6.1); extra == 'dev'
Requires-Dist: sphinx-autodoc-typehints; extra == 'dev'
Requires-Dist: sphinx-rtd-theme; extra == 'dev'
Requires-Dist: sphinxcontrib-zopeext; extra == 'dev'
Requires-Dist: zest.releaser[recommended]; extra == 'dev'
Provides-Extra: test
Requires-Dist: codecov; extra == 'test'
Requires-Dist: flake8; extra == 'test'
Requires-Dist: pytest (>=3.0); extra == 'test'
Requires-Dist: pytest-runner; extra == 'test'
Requires-Dist: coverage; extra == 'test'
Requires-Dist: flaky; extra == 'test'
Requires-Dist: isort; extra == 'test'
Requires-Dist: pytest-cov; extra == 'test'
Requires-Dist: pytest-runner; extra == 'test'
Requires-Dist: pytest-splinter; extra == 'test'
Requires-Dist: pytest-timeout; extra == 'test'
Requires-Dist: webtest; extra == 'test'
